blx/__init__.py
blx/app.py
blx/cid.py
blx/cli.py
blx/env.py
blx/file_digest.py
blx/filepath.py
blx/progress.py
blx/regex.py
blx/service_exit.py
blx-0.2.0.dist-info/LICENSE
blx-0.2.0.dist-info/WHEEL
blx-0.2.0.dist-info/entry_points.txt
blx-0.2.0.dist-info/METADATA
blx-0.2.0.dist-info/RECORD
