Metadata-Version: 2.1
Name: blx
Version: 0.2.0
Summary: Make BLOBs globally accessible
License: MIT
Author: Danilo Horta
Author-email: danilo.horta@pm.me
Requires-Python: >=3.9,<4.0
Classifier: License :: OSI Approved :: MIT License
Classifier: Programming Language :: Python :: 3
Classifier: Programming Language :: Python :: 3.9
Classifier: Programming Language :: Python :: 3.10
Classifier: Programming Language :: Python :: 3.11
Requires-Dist: minio (>=7.1.13)
Requires-Dist: pydantic (>=1.10.5)
Requires-Dist: python-dotenv (>=0.21.0)
Requires-Dist: typer[all] (>=0.7.0)
